ifood/__init__.py
ifood/exception/__init__.py
ifood/exception/ifood_exception.py
ifood/exception/validation_ifood_exception.py
ifood/model/__init__.py
ifood/model/authentication/__init__.py
ifood/model/authentication/token.py
ifood/model/catalog/__init__.py
ifood/model/financial/__init__.py
ifood/model/merchant/__init__.py
ifood/model/order/__init__.py
ifood/model/order/event.py
ifood/model/order/order.py
ifood/repository/__init__.py
ifood/repository/url_repository.py
ifood/serializer/__init__.py
ifood/serializer/ifood_serializer.py
ifood/service/__init__.py
ifood/service/authentication_service.py
ifood/service/base_service.py
ifood/service/catalog_service.py
ifood/service/financial_service.py
ifood/service/ifood_service.py
ifood/service/merchant_service.py
ifood/service/order_service.py
ifood/utils/__init__.py
ifood/utils/utils.py
sdk_ifood-1.0.0a20.dist-info/LICENSE
sdk_ifood-1.0.0a20.dist-info/METADATA
sdk_ifood-1.0.0a20.dist-info/WHEEL
sdk_ifood-1.0.0a20.dist-info/top_level.txt
sdk_ifood-1.0.0a20.dist-info/RECORD
