Metadata-Version: 2.1
Name: sdk-ifood
Version: 1.0.0a20
Summary: SDK com as features da API do IFood
Home-page: https://github.com/etraudm/sdk-ifood-python.git
Author: Micael Duarte
Author-email: dev.etraud@gmail.com
License: MIT
Project-URL: Código fonte, https://github.com/etraudm/sdk-ifood-python.git
Keywords: sdk ifood python api merchant financial catalog order developer
Platform: UNKNOWN
Classifier: Development Status :: 5 - Production/Stable
Classifier: Intended Audience :: Developers
Classifier: License :: OSI Approved :: MIT License
Classifier: Natural Language :: Portuguese (Brazilian)
Classifier: Operating System :: OS Independent
Classifier: Topic :: Software Development :: Internationalization
Classifier: Topic :: Scientific/Engineering :: Physics
Requires-Dist: requests
